nonebot_adapter_walleq-0.2.0.dist-info/METADATA
nonebot_adapter_walleq-0.2.0.dist-info/WHEEL
nonebot_adapter_walleq-0.2.0.dist-info/license_files/LICENSE
nonebot_adapter_walleq/nonebot_adapter_walleq.pyi
nonebot_adapter_walleq/__init__.py
nonebot_adapter_walleq/nonebot_adapter_walleq.abi3.so
nonebot_adapter_walleq-0.2.0.dist-info/RECORD
