Metadata-Version: 2.1
Name: nonebot-adapter-walleq
Version: 0.2.0
Requires-Dist: nonebot-adapter-onebot~=2.2.2
Requires-Dist: nonebot-plugin-localstore>=0.4.1
License-File: LICENSE
Summary: Just run walle-q in nonebot2
Keywords: nonebot,nonebot2,bot,walleq
Author-email: AbrahumLink <307887491@qq.com>
Requires-Python: >=3.8
Project-URL: hongpage, https://github.com/onebot-walle/nonebot_adapter_walleq
Project-URL: repository, https://github.com/onebot-walle/nonebot_adapter_walleq
Project-URL: documentation, https://github.com/onebot-walle/nonebot_adapter_walleq#readme
